drb_impl_wcs/__init__.py
drb_impl_wcs/_version.py
drb_impl_wcs/cortex.yml
drb_impl_wcs/exceptions.py
drb_impl_wcs/factory.py
drb_impl_wcs/wcs_nodes.py
drb_impl_wcs-1.0.0.data/data/requirements.txt
drb_impl_wcs-1.0.0.dist-info/METADATA
drb_impl_wcs-1.0.0.dist-info/WHEEL
drb_impl_wcs-1.0.0.dist-info/entry_points.txt
drb_impl_wcs-1.0.0.dist-info/top_level.txt
drb_impl_wcs-1.0.0.dist-info/RECORD
